vivodict/__init__.py
vivodict/vivodict.py
vivodict-0.3.1.dist-info/DESCRIPTION.rst
vivodict-0.3.1.dist-info/METADATA
vivodict-0.3.1.dist-info/RECORD
vivodict-0.3.1.dist-info/WHEEL
vivodict-0.3.1.dist-info/metadata.json
vivodict-0.3.1.dist-info/top_level.txt
