Metadata-Version: 2.0
Name: vivodict
Version: 0.3.1
Summary: Auto-vivified arbitrarily-nested dictionary (`dict`) classes.
Home-page: https://github.com/somada141/vivodict
Author: Adamos Kyriakou
Author-email: somada141@gmail.com
License: MIT license
Keywords: vivodict
Platform: UNKNOWN
Classifier: Development Status :: 2 - Pre-Alpha
Classifier: Intended Audience :: Developers
Classifier: License :: OSI Approved :: MIT License
Classifier: Natural Language :: English
Classifier: Programming Language :: Python :: 2
Classifier: Programming Language :: Python :: 2.6
Classifier: Programming Language :: Python :: 2.7
Classifier: Programming Language :: Python :: 3
Classifier: Programming Language :: Python :: 3.3
Classifier: Programming Language :: Python :: 3.4
Classifier: Programming Language :: Python :: 3.5
